.gitignore
LICENSE
MANIFEST.in
README.md
setup.py
materialsdatabank/__init__.py
materialsdatabank/girder_worker.py
materialsdatabank.egg-info/PKG-INFO
materialsdatabank.egg-info/SOURCES.txt
materialsdatabank.egg-info/dependency_links.txt
materialsdatabank.egg-info/entry_points.txt
materialsdatabank.egg-info/requires.txt
materialsdatabank.egg-info/top_level.txt
materialsdatabank/r1/Calc_R1_facts_sepFA_oldFePt_Main1.py
materialsdatabank/r1/__init__.py
materialsdatabank/r1/calc_R1_function_python_GEN.py
materialsdatabank/r1/fparameters_python.py
materialsdatabank/r1/gen.py
materialsdatabank/r1/test.py
materialsdatabank/tasks/__init__.py
materialsdatabank/utility/__init__.py